lmdb_dict/__about__.py
lmdb_dict/__init__.py
lmdb_dict/cache.py
lmdb_dict/mapping/__init__.py
lmdb_dict/mapping/abc.py
lmdb_dict/mapping/cached.py
lmdb_dict/mapping/safe.py
lmdb_dict/mapping/str.py
lmdb_dict/util/__init__.py
lmdb_dict/util/bstr.py
lmdb_dict/util/lock_pool.py
lmdb_dict/util/wrapper.py
lmdb_dict_full-1.0.2.dist-info/METADATA
lmdb_dict_full-1.0.2.dist-info/WHEEL
lmdb_dict_full-1.0.2.dist-info/licenses/LICENSE
lmdb_dict_full-1.0.2.dist-info/RECORD
