Metadata-Version: 2.1
Name: lmdb-dict-full
Version: 1.0.2
Summary: Full-featured Python dict interface to the LMDB "Lightning" Database.
Project-URL: Documentation, https://github.com/chicago-cdac/lmdb-dict#readme
Project-URL: Issues, https://github.com/chicago-cdac/lmdb-dict/issues
Project-URL: Source, https://github.com/chicago-cdac/lmdb-dict
Author-email: Jesse London <jesselondon@gmail.com>
License-Expression: MIT
License-File: LICENSE
Keywords: dict,lmdb
Classifier: Development Status :: 4 - Beta
Classifier: Intended Audience :: Developers
Classifier: License :: OSI Approved :: MIT License
Classifier: Programming Language :: Python
Classifier: Programming Language :: Python :: 3.8
Classifier: Programming Language :: Python :: 3.9
Classifier: Programming Language :: Python :: 3.10
Classifier: Programming Language :: Python :: 3.11
Classifier: Programming Language :: Python :: Implementation :: CPython
Classifier: Programming Language :: Python :: Implementation :: PyPy
Classifier: Topic :: Database
Classifier: Topic :: Database :: Front-Ends
Classifier: Topic :: Software Development
Classifier: Topic :: Software Development :: Libraries
Classifier: Topic :: Software Development :: Libraries :: Python Modules
Requires-Python: >=3.8
Requires-Dist: cachetools~=5.3
Requires-Dist: dickens~=2.0
Requires-Dist: lmdb>=1.4
Requires-Dist: pyyaml>=6
